{
  "$schema": "https://design-tokens.github.io/community-group/format/",
  "color": {
    "dark": {
      "paper": { "$value": "oklch(17% 0.025 310)", "$type": "color" },
      "paper-2": { "$value": "oklch(22% 0.04 310)", "$type": "color" },
      "paper-3": { "$value": "oklch(27% 0.05 310)", "$type": "color" },
      "ink": { "$value": "oklch(97% 0.018 310)", "$type": "color" },
      "ink-2": { "$value": "oklch(89% 0.025 310)", "$type": "color" },
      "muted": { "$value": "oklch(76% 0.035 310)", "$type": "color" },
      "neutral": { "$value": "oklch(69% 0.035 310)", "$type": "color" },
      "rule": { "$value": "oklch(40% 0.045 310)", "$type": "color" },
      "rule-2": { "$value": "oklch(53% 0.055 310)", "$type": "color" },
      "accent": { "$value": "oklch(80% 0.105 295)", "$type": "color" },
      "accent-readable": { "$value": "oklch(80% 0.105 295)", "$type": "color" },
      "accent-strong": { "$value": "oklch(89% 0.065 300)", "$type": "color" },
      "accent-ink": { "$value": "oklch(20% 0.04 310)", "$type": "color" },
      "focus": { "$value": "oklch(87% 0.12 295)", "$type": "color" },
      "support": { "$value": "oklch(61% 0.16 350)", "$type": "color" },
      "support-readable": { "$value": "oklch(61% 0.16 350)", "$type": "color" },
      "support-ink": { "$value": "oklch(98% 0.015 350)", "$type": "color" },
      "available": { "$value": "oklch(78% 0.12 165)", "$type": "color" },
      "available-readable": { "$value": "oklch(78% 0.12 165)", "$type": "color" },
      "available-ink": { "$value": "oklch(21% 0.04 165)", "$type": "color" },
      "warn": { "$value": "oklch(80% 0.105 80)", "$type": "color" },
      "warn-readable": { "$value": "oklch(80% 0.105 80)", "$type": "color" },
      "warn-ink": { "$value": "oklch(24% 0.045 70)", "$type": "color" },
      "sold": { "$value": "oklch(65% 0.15 10)", "$type": "color" },
      "sold-readable": { "$value": "oklch(70% 0.13 10)", "$type": "color" },
      "sold-ink": { "$value": "oklch(98% 0.018 10)", "$type": "color" },
      "closed": { "$value": "oklch(62% 0.055 300)", "$type": "color" },
      "closed-readable": { "$value": "oklch(72% 0.055 300)", "$type": "color" },
      "closed-ink": { "$value": "oklch(96% 0.018 300)", "$type": "color" }
    },
    "light": {
      "paper": { "$value": "oklch(97% 0.018 310)", "$type": "color" },
      "paper-2": { "$value": "oklch(94% 0.03 310)", "$type": "color" },
      "paper-3": { "$value": "oklch(91% 0.04 310)", "$type": "color" },
      "ink": { "$value": "oklch(30% 0.055 310)", "$type": "color" },
      "ink-2": { "$value": "oklch(37% 0.05 310)", "$type": "color" },
      "muted": { "$value": "oklch(43% 0.045 310)", "$type": "color" },
      "neutral": { "$value": "oklch(49% 0.04 310)", "$type": "color" },
      "rule": { "$value": "oklch(82% 0.035 310)", "$type": "color" },
      "rule-2": { "$value": "oklch(68% 0.05 310)", "$type": "color" },
      "accent": { "$value": "oklch(72% 0.105 295)", "$type": "color" },
      "accent-readable": { "$value": "oklch(46% 0.16 295)", "$type": "color" },
      "accent-strong": { "$value": "oklch(61% 0.12 295)", "$type": "color" },
      "accent-ink": { "$value": "oklch(27% 0.055 310)", "$type": "color" },
      "focus": { "$value": "oklch(53% 0.18 295)", "$type": "color" },
      "support": { "$value": "oklch(56% 0.16 350)", "$type": "color" },
      "support-readable": { "$value": "oklch(52% 0.16 350)", "$type": "color" },
      "support-ink": { "$value": "oklch(98% 0.015 350)", "$type": "color" },
      "available": { "$value": "oklch(67% 0.13 165)", "$type": "color" },
      "available-readable": { "$value": "oklch(47% 0.12 165)", "$type": "color" },
      "available-ink": { "$value": "oklch(21% 0.04 165)", "$type": "color" },
      "warn": { "$value": "oklch(67% 0.12 80)", "$type": "color" },
      "warn-readable": { "$value": "oklch(48% 0.12 80)", "$type": "color" },
      "warn-ink": { "$value": "oklch(24% 0.045 70)", "$type": "color" },
      "sold": { "$value": "oklch(59% 0.16 10)", "$type": "color" },
      "sold-readable": { "$value": "oklch(51% 0.16 10)", "$type": "color" },
      "sold-ink": { "$value": "oklch(98% 0.018 10)", "$type": "color" },
      "closed": { "$value": "oklch(57% 0.065 300)", "$type": "color" },
      "closed-readable": { "$value": "oklch(48% 0.065 300)", "$type": "color" },
      "closed-ink": { "$value": "oklch(96% 0.018 300)", "$type": "color" }
    }
  },
  "font": {
    "display": { "$value": "system-ui, -apple-system, BlinkMacSystemFont, Segoe UI, sans-serif", "$type": "fontFamily" },
    "body": { "$value": "system-ui, -apple-system, BlinkMacSystemFont, Segoe UI, sans-serif", "$type": "fontFamily" }
  },
  "space": {
    "3xs": { "$value": "0.25rem", "$type": "dimension" },
    "2xs": { "$value": "0.5rem", "$type": "dimension" },
    "xs": { "$value": "0.75rem", "$type": "dimension" },
    "sm": { "$value": "1rem", "$type": "dimension" },
    "md": { "$value": "1.5rem", "$type": "dimension" },
    "lg": { "$value": "2rem", "$type": "dimension" },
    "xl": { "$value": "2.5rem", "$type": "dimension" },
    "2xl": { "$value": "4rem", "$type": "dimension" },
    "3xl": { "$value": "6rem", "$type": "dimension" }
  },
  "size": {
    "text-xs": { "$value": "0.75rem", "$type": "dimension" },
    "text-sm": { "$value": "0.875rem", "$type": "dimension" },
    "text-base": { "$value": "1rem", "$type": "dimension" },
    "text-md": { "$value": "1.25rem", "$type": "dimension" },
    "text-lg": { "$value": "1.5rem", "$type": "dimension" },
    "text-xl": { "$value": "2rem", "$type": "dimension" },
    "text-display": { "$value": "3.25rem", "$type": "dimension" }
  },
  "duration": {
    "micro": { "$value": "120ms", "$type": "duration" },
    "short": { "$value": "220ms", "$type": "duration" },
    "long": { "$value": "420ms", "$type": "duration" }
  },
  "radius": {
    "card": { "$value": "1.125rem", "$type": "dimension" },
    "panel": { "$value": "1.75rem", "$type": "dimension" },
    "input": { "$value": "0.75rem", "$type": "dimension" },
    "pill": { "$value": "999px", "$type": "dimension" }
  },
  "rule": {
    "hair": { "$value": "1px", "$type": "dimension" },
    "fine": { "$value": "2px", "$type": "dimension" }
  },
  "easing": {
    "out": { "$value": [0.16, 1, 0.3, 1], "$type": "cubicBezier" },
    "in": { "$value": [0.7, 0, 0.84, 0], "$type": "cubicBezier" },
    "in-out": { "$value": [0.65, 0, 0.35, 1], "$type": "cubicBezier" }
  }
}
